PyQtUIkit/__init__.py
PyQtUIkit/_icons.py
PyQtUIkit/_translate.py
PyQtUIkit/builder/__init__.py
PyQtUIkit/builder/builder_class.py
PyQtUIkit/builder/builder_module.py
PyQtUIkit/core/__init__.py
PyQtUIkit/core/_version.py
PyQtUIkit/core/font.py
PyQtUIkit/core/icon.py
PyQtUIkit/core/properties.py
PyQtUIkit/fonts/Roboto-Black.ttf
PyQtUIkit/fonts/Roboto-BlackItalic.ttf
PyQtUIkit/fonts/Roboto-Bold.ttf
PyQtUIkit/fonts/Roboto-BoldItalic.ttf
PyQtUIkit/fonts/Roboto-Italic.ttf
PyQtUIkit/fonts/Roboto-Light.ttf
PyQtUIkit/fonts/Roboto-LightItalic.ttf
PyQtUIkit/fonts/Roboto-Medium.ttf
PyQtUIkit/fonts/Roboto-MediumItalic.ttf
PyQtUIkit/fonts/Roboto-Regular.ttf
PyQtUIkit/fonts/Roboto-Thin.ttf
PyQtUIkit/fonts/Roboto-ThinItalic.ttf
PyQtUIkit/fonts/RobotoMono-Bold.ttf
PyQtUIkit/fonts/RobotoMono-BoldItalic.ttf
PyQtUIkit/fonts/RobotoMono-ExtraLight.ttf
PyQtUIkit/fonts/RobotoMono-ExtraLightItalic.ttf
PyQtUIkit/fonts/RobotoMono-Italic.ttf
PyQtUIkit/fonts/RobotoMono-Light.ttf
PyQtUIkit/fonts/RobotoMono-LightItalic.ttf
PyQtUIkit/fonts/RobotoMono-Medium.ttf
PyQtUIkit/fonts/RobotoMono-MediumItalic.ttf
PyQtUIkit/fonts/RobotoMono-Regular.ttf
PyQtUIkit/fonts/RobotoMono-SemiBold.ttf
PyQtUIkit/fonts/RobotoMono-SemiBoldItalic.ttf
PyQtUIkit/fonts/RobotoMono-Thin.ttf
PyQtUIkit/fonts/RobotoMono-ThinItalic.ttf
PyQtUIkit/themes/__init__.py
PyQtUIkit/themes/builtin_themes.py
PyQtUIkit/themes/icons.py
PyQtUIkit/themes/languages.py
PyQtUIkit/themes/locale.py
PyQtUIkit/themes/svg.py
PyQtUIkit/themes/theme.py
PyQtUIkit/widgets/__init__.py
PyQtUIkit/widgets/_application.py
PyQtUIkit/widgets/_button.py
PyQtUIkit/widgets/_checkbox.py
PyQtUIkit/widgets/_combo_box.py
PyQtUIkit/widgets/_dialog.py
PyQtUIkit/widgets/_flow_layout.py
PyQtUIkit/widgets/_form.py
PyQtUIkit/widgets/_grid_layout.py
PyQtUIkit/widgets/_group.py
PyQtUIkit/widgets/_icon_widget.py
PyQtUIkit/widgets/_image_viewer.py
PyQtUIkit/widgets/_label.py
PyQtUIkit/widgets/_layout.py
PyQtUIkit/widgets/_line_edit.py
PyQtUIkit/widgets/_list_widget.py
PyQtUIkit-2.11.3.dist-info/LICENSE
PyQtUIkit-2.11.3.dist-info/METADATA
PyQtUIkit-2.11.3.dist-info/WHEEL
PyQtUIkit-2.11.3.dist-info/entry_points.txt
PyQtUIkit-2.11.3.dist-info/top_level.txt
PyQtUIkit-2.11.3.dist-info/RECORD
