Metadata-Version: 2.1
Name: PyQtUIkit
Version: 2.11.3
Summary: A PyQtUIkit package.
Home-page: https://github.com/SergeiKrivko
Author: SergeiKrivko
License: MIT License
Requires-Python: >=3.10
License-File: LICENSE
Requires-Dist: PyQt6 ==6.6.1
Requires-Dist: PyQt6-Qt6 ==6.6.2
Requires-Dist: beautifulsoup4
Requires-Dist: qasync
Requires-Dist: lxml
